expelliarmus.cp310-win32.pyd
expelliarmus/__init__.py
expelliarmus/utils.py
expelliarmus/wizard/__init__.py
expelliarmus/wizard/clib.py
expelliarmus/wizard/wizard.py
expelliarmus/wizard/wizard_wrapper.py
expelliarmus-1.1.12.dist-info/LICENSE
expelliarmus-1.1.12.dist-info/METADATA
expelliarmus-1.1.12.dist-info/WHEEL
expelliarmus-1.1.12.dist-info/top_level.txt
expelliarmus-1.1.12.dist-info/RECORD
