Metadata-Version: 2.1
Name: expelliarmus
Version: 1.1.12
Summary: UNKNOWN
Home-page: https://github.com/open-neuromorphic/expelliarmus
Author: Fabrizio Ottati, Gregor Lenz
Author-email: fabriziottati@gmail.com, mail@lenzgregor.com
Maintainer: Fabrizio Ottati, Gregor Lenz
Maintainer-email: fabriziottati@gmail.com, mail@lenzgregor.com
License: UNKNOWN
Platform: UNKNOWN
License-File: LICENSE
Requires-Dist: numpy
